[
    {
        "key": "group_product_review_gtacf",
        "title": "Product Review",
        "fields": [
            {
                "key": "field_product_name",
                "label": "Product Name",
                "name": "product_name",
                "aria-label": "",
                "type": "text",
                "instructions": "",
                "required": false,
                "conditional_logic": false,
                "wrapper": {
                    "width": "",
                    "class": "",
                    "id": ""
                },
                "default_value": "",
                "maxlength": "",
                "placeholder": "",
                "prepend": "",
                "append": ""
            },
            {
                "key": "field_product_image",
                "label": "Product Image",
                "name": "product_image",
                "aria-label": "",
                "type": "image",
                "instructions": "",
                "required": false,
                "conditional_logic": false,
                "wrapper": {
                    "width": "",
                    "class": "",
                    "id": ""
                },
                "return_format": "id",
                "preview_size": "medium",
                "library": "all",
                "min_width": 0,
                "min_height": 0,
                "min_size": 0,
                "max_width": 0,
                "max_height": 0,
                "max_size": 0,
                "mime_types": "",
                "uploader": "",
                "acfe_thumbnail": 0,
                "upload_folder": ""
            },
            {
                "key": "field_overall_rating",
                "label": "Overall Rating",
                "name": "overall_rating",
                "aria-label": "",
                "type": "number",
                "instructions": "",
                "required": false,
                "conditional_logic": false,
                "wrapper": {
                    "width": "",
                    "class": "",
                    "id": ""
                },
                "min": 0,
                "max": 5,
                "step": 0.5,
                "default_value": "",
                "placeholder": "",
                "prepend": "",
                "append": ""
            },
            {
                "key": "field_features",
                "label": "Features",
                "name": "features",
                "aria-label": "",
                "type": "repeater",
                "instructions": "",
                "required": false,
                "conditional_logic": false,
                "wrapper": {
                    "width": "",
                    "class": "",
                    "id": ""
                },
                "min": 0,
                "max": 0,
                "rows_per_page": 20,
                "layout": "table",
                "button_label": "Add Row",
                "collapsed": "",
                "sub_fields": [
                    {
                        "key": "field_feature_name",
                        "label": "Feature Name",
                        "name": "feature_name",
                        "aria-label": "",
                        "type": "text",
                        "instructions": "",
                        "required": false,
                        "conditional_logic": false,
                        "wrapper": {
                            "width": "",
                            "class": "",
                            "id": ""
                        },
                        "default_value": "",
                        "maxlength": "",
                        "placeholder": "",
                        "prepend": "",
                        "append": "",
                        "parent_repeater": "field_features"
                    },
                    {
                        "key": "field_feature_rating",
                        "label": "Feature Rating",
                        "name": "feature_rating",
                        "aria-label": "",
                        "type": "number",
                        "instructions": "",
                        "required": false,
                        "conditional_logic": false,
                        "wrapper": {
                            "width": "",
                            "class": "",
                            "id": ""
                        },
                        "min": 0,
                        "max": 5,
                        "step": 0.5,
                        "default_value": "",
                        "placeholder": "",
                        "prepend": "",
                        "append": "",
                        "parent_repeater": "field_features"
                    }
                ],
                "acfe_repeater_stylised_button": 0
            },
            {
                "key": "field_pros",
                "label": "Pros",
                "name": "pros",
                "aria-label": "",
                "type": "repeater",
                "instructions": "",
                "required": false,
                "conditional_logic": false,
                "wrapper": {
                    "width": "",
                    "class": "",
                    "id": ""
                },
                "min": 0,
                "max": 0,
                "rows_per_page": 20,
                "layout": "table",
                "button_label": "Add Row",
                "collapsed": "",
                "sub_fields": [
                    {
                        "key": "field_pro_text",
                        "label": "Pro",
                        "name": "pro_text",
                        "aria-label": "",
                        "type": "text",
                        "instructions": "",
                        "required": false,
                        "conditional_logic": false,
                        "wrapper": {
                            "width": "",
                            "class": "",
                            "id": ""
                        },
                        "default_value": "",
                        "maxlength": "",
                        "placeholder": "",
                        "prepend": "",
                        "append": "",
                        "parent_repeater": "field_pros"
                    }
                ],
                "acfe_repeater_stylised_button": 0
            },
            {
                "key": "field_cons",
                "label": "Cons",
                "name": "cons",
                "aria-label": "",
                "type": "repeater",
                "instructions": "",
                "required": false,
                "conditional_logic": false,
                "wrapper": {
                    "width": "",
                    "class": "",
                    "id": ""
                },
                "min": 0,
                "max": 0,
                "rows_per_page": 20,
                "layout": "table",
                "button_label": "Add Row",
                "collapsed": "",
                "sub_fields": [
                    {
                        "key": "field_con_text",
                        "label": "Con",
                        "name": "con_text",
                        "aria-label": "",
                        "type": "text",
                        "instructions": "",
                        "required": false,
                        "conditional_logic": false,
                        "wrapper": {
                            "width": "",
                            "class": "",
                            "id": ""
                        },
                        "default_value": "",
                        "maxlength": "",
                        "placeholder": "",
                        "prepend": "",
                        "append": "",
                        "parent_repeater": "field_cons"
                    }
                ],
                "acfe_repeater_stylised_button": 0
            },
            {
                "key": "field_summary",
                "label": "Summary",
                "name": "summary",
                "aria-label": "",
                "type": "textarea",
                "instructions": "",
                "required": false,
                "conditional_logic": false,
                "wrapper": {
                    "width": "",
                    "class": "",
                    "id": ""
                },
                "default_value": "",
                "new_lines": "",
                "maxlength": "",
                "placeholder": "",
                "rows": "",
                "acfe_textarea_code": 0
            },
            {
                "key": "field_author_name",
                "label": "Author Name",
                "name": "author_name",
                "aria-label": "",
                "type": "text",
                "instructions": "",
                "required": false,
                "conditional_logic": false,
                "wrapper": {
                    "width": "",
                    "class": "",
                    "id": ""
                },
                "default_value": "",
                "maxlength": "",
                "placeholder": "",
                "prepend": "",
                "append": ""
            },
            {
                "key": "field_enable_json",
                "label": "Enable JSON-LD",
                "name": "enable_json_ld",
                "aria-label": "",
                "type": "true_false",
                "instructions": "",
                "required": false,
                "conditional_logic": false,
                "wrapper": {
                    "width": "",
                    "class": "",
                    "id": ""
                },
                "ui": 1,
                "default_value": 0,
                "message": "",
                "ui_on_text": "",
                "ui_off_text": "",
                "style": ""
            },
            {
                "key": "field_67a5e611f8da0",
                "label": "Offer URL",
                "name": "offer_url",
                "aria-label": "",
                "type": "url",
                "instructions": "",
                "required": 0,
                "conditional_logic": 0,
                "wrapper": {
                    "width": "",
                    "class": "",
                    "id": ""
                },
                "default_value": "",
                "allow_in_bindings": 0,
                "placeholder": ""
            },
            {
                "key": "field_67a5e630f8da1",
                "label": "Offer Price Currency",
                "name": "offer_price_currency",
                "aria-label": "",
                "type": "text",
                "instructions": "",
                "required": 0,
                "conditional_logic": 0,
                "wrapper": {
                    "width": "",
                    "class": "",
                    "id": ""
                },
                "default_value": "USD",
                "maxlength": "",
                "allow_in_bindings": 0,
                "placeholder": "",
                "prepend": "",
                "append": ""
            },
            {
                "key": "field_67a5e644f8da2",
                "label": "Offer Price",
                "name": "offer_price",
                "aria-label": "",
                "type": "number",
                "instructions": "",
                "required": 0,
                "conditional_logic": 0,
                "wrapper": {
                    "width": "",
                    "class": "",
                    "id": ""
                },
                "default_value": "",
                "min": "",
                "max": "",
                "allow_in_bindings": 0,
                "placeholder": "",
                "step": "",
                "prepend": "",
                "append": ""
            },
            {
                "key": "field_67a5e710c7bf4",
                "label": "Offer CTA Text",
                "name": "offer_cta_text",
                "aria-label": "",
                "type": "text",
                "instructions": "",
                "required": 0,
                "conditional_logic": 0,
                "wrapper": {
                    "width": "",
                    "class": "",
                    "id": ""
                },
                "default_value": "",
                "maxlength": "",
                "allow_in_bindings": 0,
                "placeholder": "",
                "prepend": "",
                "append": ""
            },
            {
                "key": "field_67a5eb2c4e9c6",
                "label": "Payment Term",
                "name": "payment_term",
                "aria-label": "",
                "type": "text",
                "instructions": "",
                "required": 0,
                "conditional_logic": 0,
                "wrapper": {
                    "width": "",
                    "class": "",
                    "id": ""
                },
                "default_value": "Per Month",
                "maxlength": "",
                "allow_in_bindings": 0,
                "placeholder": "",
                "prepend": "",
                "append": ""
            }
        ],
        "location": [
            [
                {
                    "param": "block",
                    "operator": "==",
                    "value": "acf\/product-review"
                }
            ]
        ],
        "menu_order": 0,
        "position": "normal",
        "style": "default",
        "label_placement": "top",
        "instruction_placement": "label",
        "hide_on_screen": "",
        "active": true,
        "description": "",
        "show_in_rest": 0
    }
]
